slicot/py.typed
slicot/_slicot.cp312-win_amd64.dll.a
slicot/_slicot.cp312-win_amd64.pyd
slicot/__init__.py
slicot-1.0.11.dist-info/DELVEWHEEL
slicot-1.0.11.dist-info/METADATA
slicot-1.0.11.dist-info/RECORD
slicot-1.0.11.dist-info/WHEEL
slicot-1.0.11.dist-info/licenses/LICENSE
slicot.libs/libgcc_s_seh-1-8ac28fe21ad5783af7630f2f0c8f554d.dll
slicot.libs/libscipy_openblas-197ee2fc9b4d071f7e048078cac74115.dll
slicot.libs/libwinpthread-1-e271f374468d584905afcdf7da96a6ad.dll
