Metadata-Version: 2.4
Name: slicot
Version: 1.0.11
Summary: Python bindings for SLICOT - Subroutine Library in Control Theory
Keywords: control,systems,linear,lapack,blas,riccati,lyapunov
Author: SLICOT Contributors
License-Expression: BSD-3-Clause
License-File: LICENSE
Classifier: Development Status :: 5 - Production/Stable
Classifier: Intended Audience :: Science/Research
Classifier: Intended Audience :: Developers
Classifier: Operating System :: OS Independent
Classifier: Programming Language :: C
Classifier: Programming Language :: Python :: 3
Classifier: Programming Language :: Python :: 3.11
Classifier: Programming Language :: Python :: 3.12
Classifier: Programming Language :: Python :: 3.13
Classifier: Programming Language :: Python :: 3.14
Classifier: Topic :: Scientific/Engineering
Classifier: Topic :: Scientific/Engineering :: Mathematics
Project-URL: Homepage, https://github.com/jamestjsp/slicot
Project-URL: Documentation, https://slicot.readthedocs.io/
Project-URL: Repository, https://github.com/jamestjsp/slicot
Project-URL: Issues, https://github.com/jamestjsp/slicot/issues
Requires-Python: >=3.11
Requires-Dist: numpy>=2.0
Provides-Extra: test
Requires-Dist: pytest; extra == "test"
Requires-Dist: pytest-xdist; extra == "test"
Requires-Dist: pytest-rerunfailures; extra == "test"
Requires-Dist: scipy; extra == "test"
Provides-Extra: benchmark
Requires-Dist: pytest-benchmark>=4.0; extra == "benchmark"
Provides-Extra: dev
Requires-Dist: meson-python>=0.16.0; extra == "dev"
Requires-Dist: meson>=1.1.0; extra == "dev"
Requires-Dist: ninja; extra == "dev"
Requires-Dist: numpy>=2.0; extra == "dev"
Requires-Dist: scipy-openblas32; extra == "dev"
